LICENSE
README.md
setup.py
everpay/__init__.py
everpay/account.py
everpay/bundle.py
everpay/client.py
everpay/signer.py
everpay/token.py
everpay/transaction.py
everpay/utils.py
everpay.egg-info/PKG-INFO
everpay.egg-info/SOURCES.txt
everpay.egg-info/dependency_links.txt
everpay.egg-info/requires.txt
everpay.egg-info/top_level.txt