Metadata-Version: 2.1
Name: everpay
Version: 0.2.1
Summary: Python wrappers for everpay.io api
Home-page: https://github.com/everFinance/everpay.py
Author: xiaojay
Author-email: xiaojay@gmail.com
License: MIT
Download-URL: https://github.com/everFinance/everpay.py/archive/refs/tags/v0.2.1.tar.gz
Platform: UNKNOWN
Classifier: Programming Language :: Python :: 3
Classifier: Programming Language :: Python :: 2
Classifier: License :: OSI Approved :: MIT License
Classifier: Operating System :: OS Independent
License-File: LICENSE
